pygame_framework/__init__.py
pygame_framework/config.py
pygame_framework/game.py
pygame_framework/assets/Icon.png
pygame_framework/assets/__init__.py
pygame_framework/components/__init__.py
pygame_framework/components/base_component.py
pygame_framework/components/renderer_component.py
pygame_framework/components/transform_component.py
pygame_framework/core/__init__.py
pygame_framework/core/asset_manager.py
pygame_framework/core/renderer.py
pygame_framework/core/scene_manager.py
pygame_framework/core/window.py
pygame_framework/game_object/__init__.py
pygame_framework/game_object/base_object.py
pygame_framework/scenes/__init__.py
pygame_framework/scenes/base_scene.py
pygame_framework_1just_josh-0.0.11.dist-info/METADATA
pygame_framework_1just_josh-0.0.11.dist-info/WHEEL
pygame_framework_1just_josh-0.0.11.dist-info/top_level.txt
pygame_framework_1just_josh-0.0.11.dist-info/RECORD
