Metadata-Version: 2.4
Name: pygame_framework_1just_josh
Version: 0.0.11
Summary: this is a simple pygame wrapper for advanced game features with less boilerplate
Author: Joshua - jjboy2245
License: Apache-2.0
Classifier: License :: OSI Approved :: Apache Software License
Requires-Python: >=3.7
Requires-Dist: pygame-ce
Requires-Dist: msgpack
Requires-Dist: cryptography
Dynamic: author
Dynamic: classifier
Dynamic: description
Dynamic: description-content-type
Dynamic: license
Dynamic: requires-dist
Dynamic: requires-python
Dynamic: summary
